kea2/__init__.py
kea2/adbUtils.py
kea2/cli.py
kea2/fastbotManager.py
kea2/kea2_api.py
kea2/keaUtils.py
kea2/kea_launcher.py
kea2/logWatcher.py
kea2/mixin.py
kea2/result.py
kea2/resultSyncer.py
kea2/state.py
kea2/typedefs.py
kea2/u2Driver.py
kea2/utils.py
kea2/version_manager.py
kea2/assets/config_version.json
kea2/assets/fastbot-thirdpart.jar
kea2/assets/framework.jar
kea2/assets/kea2-thirdpart.jar
kea2/assets/monkeyq.jar
kea2/assets/quicktest.py
kea2/assets/fastbot_configs/abl.strings
kea2/assets/fastbot_configs/awl.strings
kea2/assets/fastbot_configs/max.config
kea2/assets/fastbot_configs/max.fuzzing.strings
kea2/assets/fastbot_configs/max.schema.strings
kea2/assets/fastbot_configs/max.strings
kea2/assets/fastbot_configs/max.tree.pruning
kea2/assets/fastbot_configs/teardown.py
kea2/assets/fastbot_configs/widget.block.py
kea2/assets/fastbot_libs/arm64-v8a/libfastbot_native.so
kea2/assets/fastbot_libs/armeabi-v7a/libfastbot_native.so
kea2/assets/fastbot_libs/x86/libfastbot_native.so
kea2/assets/fastbot_libs/x86_64/libfastbot_native.so
kea2/report/__init__.py
kea2/report/bug_report_generator.py
kea2/report/mixin.py
kea2/report/report_merger.py
kea2/report/utils.py
kea2/report/templates/bug_report_template.html
kea2/report/templates/merged_bug_report_template.html
kea2_python-1.1.1.dist-info/licenses/LICENSE
kea2_python-1.1.1.dist-info/METADATA
kea2_python-1.1.1.dist-info/WHEEL
kea2_python-1.1.1.dist-info/entry_points.txt
kea2_python-1.1.1.dist-info/top_level.txt
kea2_python-1.1.1.dist-info/RECORD
