Metadata-Version: 2.4
Name: Kea2-python
Version: 1.1.1
Summary: A python library for supporting and customizing automated UI testing for mobile apps
Author-email: Xixian Liang <xixian@stu.ecnu.edu.cn>
Requires-Python: >=3.8
License-File: LICENSE
Requires-Dist: rtree>=1.3.0
Requires-Dist: jinja2>=3.0.0
Requires-Dist: uiautomator2>=3.3.3
Requires-Dist: adbutils>=2.9.3
Requires-Dist: packaging>=25.0
Dynamic: license-file
